LICENSE
MANIFEST.in
README.rst
setup.cfg
setup.py
django_requests_monitoring.egg-info/PKG-INFO
django_requests_monitoring.egg-info/SOURCES.txt
django_requests_monitoring.egg-info/dependency_links.txt
django_requests_monitoring.egg-info/requires.txt
django_requests_monitoring.egg-info/top_level.txt
monitoring/__init__.py
monitoring/apps.py
monitoring/middleware.py
monitoring/settings.py
monitoring/statsd.py
monitoring/__pycache__/__init__.cpython-36.pyc
monitoring/__pycache__/apps.cpython-36.pyc
monitoring/__pycache__/middleware.cpython-36.pyc
monitoring/__pycache__/settings.cpython-36.pyc
monitoring/__pycache__/statsd.cpython-36.pyc