Metadata-Version: 2.1
Name: django-requests-monitoring
Version: 0.1.0
Summary: Manage http requests metrics via StatsD.
Home-page: https://github.com/emilioag/django-requests-monitoring/
Author: emilioag
Author-email: emilioag@mail.com
License: UNKNOWN
Keywords: django statsd,monitoring
Platform: UNKNOWN
Classifier: Development Status :: 3 - Alpha
Classifier: Intended Audience :: Developers
Classifier: Topic :: Software Development :: Documentation
Classifier: License :: OSI Approved :: MIT License
Classifier: Programming Language :: Python :: 3.6
Provides-Extra: test
Provides-Extra: dev
